design.sv
// Code your design here
module synchronous_fifo #(parameter DEPTH=8, DATA_WIDTH=8) (
  input clk, rst_n,
  input w_en, r_en,
  input [DATA_WIDTH-1:0] data_in,
  output reg [DATA_WIDTH-1:0] data_out,
  output full, empty
);
  
  reg [$clog2(DEPTH)-1:0] w_ptr, r_ptr;
  reg [DATA_WIDTH-1:0] fifo[DEPTH];
  
  // Set Default values on reset.
  always@(posedge clk) begin
    if(!rst_n) begin
      w_ptr <= 0; r_ptr <= 0;
      data_out <= 0;
    end
  end
  
  // To write data to FIFO
  always@(posedge clk) begin
    if(w_en & !full)begin
      fifo[w_ptr] <= data_in;
      w_ptr <= w_ptr + 1;
    end
  end
  
  // To read data from FIFO
  always@(posedge clk) begin
    if(r_en & !empty) begin
      data_out <= fifo[r_ptr];
      r_ptr <= r_ptr + 1;
    end
  end
  
  assign full = ((w_ptr+1'b1) == r_ptr);
  assign empty = (w_ptr == r_ptr);
endmodule

testbench.sv
// Code your testbench here
// or browse Examples
module sync_fifo_TB;
  parameter DATA_WIDTH = 8;
  
  reg clk, rst_n;
  reg w_en, r_en;
  reg [DATA_WIDTH-1:0] data_in;
  wire [DATA_WIDTH-1:0] data_out;
  wire full, empty;
  
  // Queue to push data_in
  reg [DATA_WIDTH-1:0] wdata_q[$], wdata;

  synchronous_fifo s_fifo(clk, rst_n, w_en, r_en, data_in, data_out, full, empty);

  always #5 clk = ~clk;
  
  initial begin
    clk = 1'b0; rst_n = 1'b0;
    w_en = 1'b0;
    data_in = 0;
    
    repeat(10) @(posedge clk);
    rst_n = 1'b1;

    repeat(2) begin
      for (int i=0; i<30; i++) begin
        @(posedge clk);
        w_en = (i%2 == 0)? 1'b1 : 1'b0;
        if (w_en & !full) begin
          data_in = $urandom;
          wdata_q.push_back(data_in);
        end
      end
      #50;
    end
  end

  initial begin
    clk = 1'b0; rst_n = 1'b0;
    r_en = 1'b0;

    repeat(20) @(posedge clk);
    rst_n = 1'b1;

    repeat(2) begin
      for (int i=0; i<30; i++) begin
        @(posedge clk);
        r_en = (i%2 == 0)? 1'b1 : 1'b0;
        if (r_en & !empty) begin
          #1;
          wdata = wdata_q.pop_front();
          if(data_out !== wdata) $error("Time = %0t: Comparison Failed: expected wr_data = %h, rd_data = %h", $time, wdata, data_out);
          else $display("Time = %0t: Comparison Passed: wr_data = %h and rd_data = %h",$time, wdata, data_out);
        end
      end
      #50;
    end

    $finish;
  end
  
  initial begin 
    $dumpfile("dump.vcd"); $dumpvars;
  end
endmodule

dump.vcd
$date
	Fri Aug 30 11:34:59 2024
$end
$version
	Icarus Verilog
$end
$timescale
	1s
$end
$scope module sync_fifo_TB $end
$var wire 1 ! full $end
$var wire 1 " empty $end
$var wire 8 # data_out [7:0] $end
$var parameter 32 $ DATA_WIDTH $end
$var reg 1 % clk $end
$var reg 8 & data_in [7:0] $end
$var reg 1 ' r_en $end
$var reg 1 ( rst_n $end
$var reg 1 ) w_en $end
$var reg 8 * wdata [7:0] $end
$scope module s_fifo $end
$var wire 1 % clk $end
$var wire 8 + data_in [7:0] $end
$var wire 1 ' r_en $end
$var wire 1 ( rst_n $end
$var wire 1 ) w_en $end
$var wire 1 ! full $end
$var wire 1 " empty $end
$var parameter 32 , DATA_WIDTH $end
$var parameter 32 - DEPTH $end
$var reg 8 . data_out [7:0] $end
$var reg 3 / r_ptr [2:0] $end
$var reg 3 0 w_ptr [2:0] $end
$upscope $end
$scope begin $ivl_for_loop0 $end
$var integer 32 1 i [31:0] $end
$upscope $end
$scope begin $ivl_for_loop1 $end
$var integer 32 2 i [31:0] $end
$upscope $end
$upscope $end
$enddefinitions $end
$comment Show the parameter values. $end
$dumpall
b1000 -
b1000 ,
b1000 $
$end
#0
$dumpvars
b0 2
b0 1
bx 0
bx /
bx .
b0 +
bx *
0)
0(
0'
b0 &
0%
bx #
x"
x!
$end
#5
b0 #
b0 .
0!
1"
b0 /
b0 0
1%
#10
0%
#15
1%
#20
0%
#25
1%
#30
0%
#35
1%
#40
0%
#45
1%
#50
0%
#55
1%
#60
0%
#65
1%
#70
0%
#75
1%
#80
0%
#85
1%
#90
0%
#95
1(
1%
#100
0%
#105
0"
b1 0
b1 1
b100100 &
b100100 +
1)
1%
#110
0%
#115
b10 0
b10 1
0)
1%
#120
0%
#125
b11 0
b11 1
b10000001 &
b10000001 +
1)
1%
#130
0%
#135
b100 0
b100 1
0)
1%
#140
0%
#145
b101 0
b101 1
b1001 &
b1001 +
1)
1%
#150
0%
#155
b110 0
b110 1
0)
1%
#160
0%
#165
1!
b111 0
b111 1
b1100011 &
b1100011 +
1)
1%
#170
0%
#175
b1000 1
0)
1%
#180
0%
#185
b1001 1
1)
1%
#190
0%
#195
b1010 1
0)
1%
#200
0%
#205
0!
b1 /
b100100 #
b100100 .
b1011 1
1)
1'
1%
#206
b1 2
b100100 *
#210
0%
#215
1!
b0 0
b1100 1
0)
b10 2
0'
1%
#220
0%
#225
1'
b1101 1
1)
1%
#226
b11 2
b10000001 *
#230
0%
#235
b1110 1
0)
b100 2
0'
1%
#240
0%
#245
1'
b1111 1
1)
1%
#246
b101 2
b1001 *
#250
0%
#255
b10000 1
0)
b110 2
0'
1%
#260
0%
#265
1'
b10001 1
1)
1%
#266
b111 2
b1100011 *
#270
0%
#275
b10010 1
0)
b1000 2
0'
1%
#280
0%
#285
1'
b10011 1
1)
1%
#286
b1001 2
bx *
#290
0%
#295
b10100 1
0)
b1010 2
0'
1%
#300
0%
#305
1'
b10101 1
1)
1%
#306
b1011 2
#310
0%
#315
b10110 1
0)
b1100 2
0'
1%
#320
0%
#325
1'
b10111 1
1)
1%
#326
b1101 2
#330
0%
#335
b11000 1
0)
b1110 2
0'
1%
#340
0%
#345
1'
b11001 1
1)
1%
#346
b1111 2
#350
0%
#355
b11010 1
0)
b10000 2
0'
1%
#360
0%
#365
1'
b11011 1
1)
1%
#366
b10001 2
#370
0%
#375
b11100 1
0)
b10010 2
0'
1%
#380
0%
#385
1'
b11101 1
1)
1%
#386
b10011 2
#390
0%
#395
b11110 1
0)
b10100 2
0'
1%
#400
0%
#405
1'
1%
#406
b10101 2
#410
0%
#415
b10110 2
0'
1%
#420
0%
#425
1'
1%
#426
b10111 2
#430
0%
#435
b11000 2
0'
1%
#440
0%
#445
1'
1)
1%
b1 1
#446
b11001 2
#450
0%
#455
b10 1
0)
b11010 2
0'
1%
#460
0%
#465
1'
b11 1
1)
1%
#466
b11011 2
#470
0%
#475
b100 1
0)
b11100 2
0'
1%
#480
0%
#485
1'
b101 1
1)
1%
#486
b11101 2
#490
0%
#495
b110 1
0)
b11110 2
0'
1%
#500
0%
#505
b111 1
1)
1%
#510
0%
#515
b1000 1
0)
1%
#520
0%
#525
b1001 1
1)
1%
#530
0%
#535
b1010 1
0)
1%
#540
0%
#545
0!
b10 /
b1011 1
1)
1'
1%
b0 2
#546
b1 2
#550
0%
#555
1!
b1 0
b1100 1
0)
b10 2
0'
1%
#560
0%
#565
1'
b1101 1
1)
1%
#566
b11 2
#570
0%
#575
b1110 1
0)
b100 2
0'
1%
#580
0%
#585
1'
b1111 1
1)
1%
#586
b101 2
#590
0%
#595
b10000 1
0)
b110 2
0'
1%
#600
0%
#605
1'
b10001 1
1)
1%
#606
b111 2
#610
0%
#615
b10010 1
0)
b1000 2
0'
1%
#620
0%
#625
1'
b10011 1
1)
1%
#626
b1001 2
#630
0%
#635
b10100 1
0)
b1010 2
0'
1%
#640
0%
#645
1'
b10101 1
1)
1%
#646
b1011 2
#650
0%
#655
b10110 1
0)
b1100 2
0'
1%
#660
0%
#665
1'
b10111 1
1)
1%
#666
b1101 2
#670
0%
#675
b11000 1
0)
b1110 2
0'
1%
#680
0%
#685
1'
b11001 1
1)
1%
#686
b1111 2
#690
0%
#695
b11010 1
0)
b10000 2
0'
1%
#700
0%
#705
1'
b11011 1
1)
1%
#706
b10001 2
#710
0%
#715
b11100 1
0)
b10010 2
0'
1%
#720
0%
#725
1'
b11101 1
1)
1%
#726
b10011 2
#730
0%
#735
b11110 1
0)
b10100 2
0'
1%
#740
0%
#745
1'
1%
#746
b10101 2
#750
0%
#755
b10110 2
0'
1%
#760
0%
#765
1'
1%
#766
b10111 2
#770
0%
#775
b11000 2
0'
1%
#780
0%
#785
1'
1%
#786
b11001 2
#790
0%
#795
b11010 2
0'
1%
#800
0%
#805
1'
1%
#806
b11011 2
#810
0%
#815
b11100 2
0'
1%
#820
0%
#825
1'
1%
#826
b11101 2
#830
0%
#835
b11110 2
0'
1%
